{
  "data": {
    "article": {},
    "attachments": {},
    "author_id": "1805373961020260353",
    "conversation_id": "1996455612398592075",
    "created_at": "2025-12-04T17:54:16.000Z",
    "edit_controls": {
      "editable_until": "2025-12-04T18:54:16.000Z",
      "edits_remaining": 5,
      "is_edit_eligible": false
    },
    "edit_history_tweet_ids": [
      "1996639204701622645"
    ],
    "entities": {
      "mentions": [
        {
          "end": 11,
          "id": "623965569",
          "start": 0,
          "username": "nothousand"
        }
      ]
    },
    "geo": {},
    "id": "1996639204701622645",
    "in_reply_to_user_id": "623965569",
    "lang": "ja",
    "note_tweet": {
      "entities": {}
    },
    "possibly_sensitive": false,
    "public_metrics": {
      "bookmark_count": 0,
      "impression_count": 0,
      "like_count": 0,
      "quote_count": 0,
      "reply_count": 0,
      "retweet_count": 0
    },
    "referenced_tweets": [
      {
        "id": "1996455612398592075",
        "type": "replied_to"
      }
    ],
    "reply_settings": "everyone",
    "text": "@nothousand 👀👀👀👀👀👀👀👀👀👀👀👀👀姐姐敲我"
  },
  "includes": {
    "media": [
      {
        "duration_ms": 9716,
        "height": 960,
        "media_key": "13_1996455559281934336",
        "preview_image_url": "https://pbs.twimg.com/amplify_video_thumb/1996455559281934336/img/vFKn7F4LWSdqumG6.jpg",
        "public_metrics": {
          "view_count": 254
        },
        "type": "video",
        "variants": [
          {
            "bit_rate": 632000,
            "content_type": "video/mp4",
            "url": "https://video.twimg.com/amplify_video/1996455559281934336/vid/avc1/320x426/oPogSxbdx79SGaC0.mp4"
          },
          {
            "bit_rate": 950000,
            "content_type": "video/mp4",
            "url": "https://video.twimg.com/amplify_video/1996455559281934336/vid/avc1/480x640/9IQwWF3DlG7YrIj1.mp4"
          },
          {
            "bit_rate": 2176000,
            "content_type": "video/mp4",
            "url": "https://video.twimg.com/amplify_video/1996455559281934336/vid/avc1/720x960/mrzCZnDV1XITMUSQ.mp4"
          },
          {
            "content_type": "application/x-mpegURL",
            "url": "https://video.twimg.com/amplify_video/1996455559281934336/pl/xFKVMkErCW2MGHiJ.m3u8"
          }
        ],
        "width": 720
      }
    ],
    "tweets": [
      {
        "article": {},
        "attachments": {},
        "author_id": "1805373961020260353",
        "conversation_id": "1996455612398592075",
        "created_at": "2025-12-04T17:54:16.000Z",
        "edit_controls": {
          "editable_until": "2025-12-04T18:54:16.000Z",
          "edits_remaining": 5,
          "is_edit_eligible": false
        },
        "edit_history_tweet_ids": [
          "1996639204701622645"
        ],
        "entities": {
          "mentions": [
            {
              "end": 11,
              "id": "623965569",
              "start": 0,
              "username": "nothousand"
            }
          ]
        },
        "geo": {},
        "id": "1996639204701622645",
        "in_reply_to_user_id": "623965569",
        "lang": "ja",
        "note_tweet": {
          "entities": {}
        },
        "possibly_sensitive": false,
        "public_metrics": {
          "bookmark_count": 0,
          "impression_count": 0,
          "like_count": 0,
          "quote_count": 0,
          "reply_count": 0,
          "retweet_count": 0
        },
        "referenced_tweets": [
          {
            "id": "1996455612398592075",
            "type": "replied_to"
          }
        ],
        "reply_settings": "everyone",
        "text": "@nothousand 👀👀👀👀👀👀👀👀👀👀👀👀👀姐姐敲我"
      },
      {
        "article": {},
        "attachments": {
          "media_keys": [
            "13_1996455559281934336"
          ]
        },
        "author_id": "623965569",
        "conversation_id": "1996455612398592075",
        "created_at": "2025-12-04T05:44:45.000Z",
        "edit_controls": {
          "editable_until": "2025-12-04T06:44:45.000Z",
          "edits_remaining": 5,
          "is_edit_eligible": true
        },
        "edit_history_tweet_ids": [
          "1996455612398592075"
        ],
        "entities": {
          "urls": [
            {
              "display_url": "pic.x.com/Bm681EdVej",
              "end": 34,
              "expanded_url": "https://x.com/nothousand/status/1996455612398592075/video/1",
              "media_key": "13_1996455559281934336",
              "start": 11,
              "url": "https://t.co/Bm681EdVej"
            }
          ]
        },
        "geo": {},
        "id": "1996455612398592075",
        "lang": "zh",
        "note_tweet": {
          "entities": {}
        },
        "possibly_sensitive": false,
        "public_metrics": {
          "bookmark_count": 0,
          "impression_count": 823,
          "like_count": 17,
          "quote_count": 0,
          "reply_count": 8,
          "retweet_count": 0
        },
        "reply_settings": "everyone",
        "text": "禁止视🗡️ 违者敲头 https://t.co/Bm681EdVej"
      }
    ],
    "users": [
      {
        "created_at": "2024-06-24T22:54:46.000Z",
        "description": "主包傻fufu的所以会偷吃你的大脑🧠/深夜发的消息不关素的事",
        "id": "1805373961020260353",
        "location": "基沃托斯",
        "name": "素素素素素",
        "pinned_tweet_id": "1992888264173441156",
        "profile_image_url": "https://pbs.twimg.com/profile_images/1980223146952183808/kEXCopJn_normal.jpg",
        "protected": false,
        "public_metrics": {
          "followers_count": 1535,
          "following_count": 538,
          "like_count": 9379,
          "listed_count": 4,
          "media_count": 288,
          "tweet_count": 2246
        },
        "username": "ciyou9443",
        "verified": false
      },
      {
        "created_at": "2012-07-01T16:27:02.000Z",
        "description": "/记录一些异世界的碎碎念w #INFJ ##有奇怪想法和需求的人看黄男别来关注我关了也会被我清理！！ /谨慎fo因为我们可能不是一类人，或者不是你以为的那类人喔 /不定期删除三无号，不同频的人还请见谅 /需要回fo请大胆和我说我会来仔细观察你然后给你答案 //雷自残od各种赤裸色色看到这样的人会unfo",
        "entities": {
          "description": {
            "hashtags": [
              {
                "end": 19,
                "start": 14,
                "tag": "INFJ"
              },
              {
                "end": 48,
                "start": 21,
                "tag": "有奇怪想法和需求的人看黄男别来关注我关了也会被我清理"
              }
            ]
          }
        },
        "id": "623965569",
        "location": "earth",
        "name": "芊茉音華",
        "pinned_tweet_id": "1987184865482301857",
        "profile_image_url": "https://pbs.twimg.com/profile_images/1993162808947863552/P8jx972e_normal.jpg",
        "protected": false,
        "public_metrics": {
          "followers_count": 1798,
          "following_count": 114,
          "like_count": 6324,
          "listed_count": 5,
          "media_count": 373,
          "tweet_count": 4414
        },
        "username": "nothousand",
        "verified": false
      }
    ]
  }
}