{
  "data": {
    "article": {},
    "attachments": {},
    "author_id": "1805373961020260353",
    "conversation_id": "1941872331686916493",
    "created_at": "2025-07-06T15:28:14.000Z",
    "edit_controls": {
      "editable_until": "2025-07-06T16:28:14.000Z",
      "edits_remaining": 5,
      "is_edit_eligible": false
    },
    "edit_history_tweet_ids": [
      "1941881886005223929"
    ],
    "entities": {
      "mentions": [
        {
          "end": 16,
          "id": "1812014790958829568",
          "start": 0,
          "username": "MiaoJiang080923"
        }
      ]
    },
    "geo": {},
    "id": "1941881886005223929",
    "in_reply_to_user_id": "1812014790958829568",
    "lang": "ja",
    "note_tweet": {
      "entities": {}
    },
    "possibly_sensitive": false,
    "public_metrics": {
      "bookmark_count": 0,
      "impression_count": 0,
      "like_count": 0,
      "quote_count": 0,
      "reply_count": 0,
      "retweet_count": 0
    },
    "referenced_tweets": [
      {
        "id": "1941872331686916493",
        "type": "replied_to"
      }
    ],
    "reply_settings": "everyone",
    "text": "@MiaoJiang080923 小美女～♥(｡￫v￩｡)♥"
  },
  "includes": {
    "media": [
      {
        "height": 1536,
        "media_key": "3_1941872328083636224",
        "public_metrics": {},
        "type": "photo",
        "url": "https://pbs.twimg.com/media/GvLqmAqWAAAoMD_.jpg",
        "width": 2048
      }
    ],
    "tweets": [
      {
        "article": {},
        "attachments": {},
        "author_id": "1805373961020260353",
        "conversation_id": "1941872331686916493",
        "created_at": "2025-07-06T15:28:14.000Z",
        "edit_controls": {
          "editable_until": "2025-07-06T16:28:14.000Z",
          "edits_remaining": 5,
          "is_edit_eligible": false
        },
        "edit_history_tweet_ids": [
          "1941881886005223929"
        ],
        "entities": {
          "mentions": [
            {
              "end": 16,
              "id": "1812014790958829568",
              "start": 0,
              "username": "MiaoJiang080923"
            }
          ]
        },
        "geo": {},
        "id": "1941881886005223929",
        "in_reply_to_user_id": "1812014790958829568",
        "lang": "ja",
        "note_tweet": {
          "entities": {}
        },
        "possibly_sensitive": false,
        "public_metrics": {
          "bookmark_count": 0,
          "impression_count": 0,
          "like_count": 0,
          "quote_count": 0,
          "reply_count": 0,
          "retweet_count": 0
        },
        "referenced_tweets": [
          {
            "id": "1941872331686916493",
            "type": "replied_to"
          }
        ],
        "reply_settings": "everyone",
        "text": "@MiaoJiang080923 小美女～♥(｡￫v￩｡)♥"
      },
      {
        "article": {},
        "attachments": {
          "media_keys": [
            "3_1941872328083636224"
          ]
        },
        "author_id": "1812014790958829568",
        "conversation_id": "1941872331686916493",
        "created_at": "2025-07-06T14:50:16.000Z",
        "edit_controls": {
          "editable_until": "2025-07-06T15:50:16.000Z",
          "edits_remaining": 5,
          "is_edit_eligible": true
        },
        "edit_history_tweet_ids": [
          "1941872331686916493"
        ],
        "entities": {
          "urls": [
            {
              "display_url": "pic.x.com/JqoS3LY70d",
              "end": 45,
              "expanded_url": "https://x.com/MiaoJiang080923/status/1941872331686916493/photo/1",
              "media_key": "3_1941872328083636224",
              "start": 22,
              "url": "https://t.co/JqoS3LY70d"
            }
          ]
        },
        "geo": {},
        "id": "1941872331686916493",
        "lang": "zh",
        "note_tweet": {
          "entities": {}
        },
        "possibly_sensitive": false,
        "public_metrics": {
          "bookmark_count": 0,
          "impression_count": 34,
          "like_count": 2,
          "quote_count": 0,
          "reply_count": 1,
          "retweet_count": 0
        },
        "reply_settings": "everyone",
        "text": "嘿嘿，酒吧老板娘说咱今天打扮的特别想小美女 https://t.co/JqoS3LY70d"
      }
    ],
    "users": [
      {
        "created_at": "2024-06-24T22:54:46.000Z",
        "description": "薛定谔的颜值/🏳️‍⚧️🍥/是我哦～跨女同/亲爱的大小姐 @hoshinemu123",
        "entities": {
          "description": {
            "mentions": [
              {
                "end": 42,
                "start": 29,
                "username": "hoshinemu123"
              }
            ]
          }
        },
        "id": "1805373961020260353",
        "location": "基沃托斯",
        "name": "素素素素素",
        "pinned_tweet_id": "1912156270657700280",
        "profile_image_url": "https://pbs.twimg.com/profile_images/1839325707840933888/Wj9NkqpE_normal.jpg",
        "protected": false,
        "public_metrics": {
          "followers_count": 929,
          "following_count": 375,
          "like_count": 3788,
          "listed_count": 2,
          "media_count": 111,
          "tweet_count": 1062
        },
        "username": "ciyou9443",
        "verified": false
      },
      {
        "created_at": "2024-07-13T06:42:55.000Z",
        "description": "08年药娘🍥/一个笨蛋的可爱狸花猫／\n/时不时会情绪爆炸/\n/门槛🚪30/同类免费互fo/某个笨蛋@WinkCat1234 /  永远最喜欢最爱的笨蛋姐姐  @orugannokasa  / 广州佛山随机刷新",
        "entities": {
          "description": {
            "mentions": [
              {
                "end": 61,
                "start": 49,
                "username": "WinkCat1234"
              },
              {
                "end": 92,
                "start": 79,
                "username": "orugannokasa"
              }
            ]
          }
        },
        "id": "1812014790958829568",
        "location": "广州",
        "name": "小阿元和喵酱🍥🏳️‍⚧",
        "pinned_tweet_id": "1918193003317133587",
        "profile_image_url": "https://pbs.twimg.com/profile_images/1918933948165672960/9cvSqk9A_normal.jpg",
        "protected": false,
        "public_metrics": {
          "followers_count": 655,
          "following_count": 295,
          "like_count": 219,
          "listed_count": 1,
          "media_count": 120,
          "tweet_count": 197
        },
        "username": "MiaoJiang080923",
        "verified": false
      }
    ]
  }
}