{
  "data": {
    "article": {},
    "attachments": {},
    "author_id": "1805373961020260353",
    "conversation_id": "1972598501847847301",
    "created_at": "2025-09-29T09:45:06.000Z",
    "edit_controls": {
      "editable_until": "2025-09-29T10:45:06.000Z",
      "edits_remaining": 5,
      "is_edit_eligible": true
    },
    "edit_history_tweet_ids": [
      "1972598501847847301"
    ],
    "entities": {},
    "geo": {},
    "id": "1972598501847847301",
    "lang": "zh",
    "note_tweet": {
      "entities": {}
    },
    "possibly_sensitive": false,
    "public_metrics": {
      "bookmark_count": 0,
      "impression_count": 0,
      "like_count": 0,
      "quote_count": 0,
      "reply_count": 0,
      "retweet_count": 0
    },
    "reply_settings": "everyone",
    "text": "由于最近眠大人最近再网上和多人吵架，收到不明快递之后以为是炸弹💣(≧ω≦)/"
  },
  "includes": {
    "tweets": [
      {
        "article": {},
        "attachments": {},
        "author_id": "1805373961020260353",
        "conversation_id": "1972598501847847301",
        "created_at": "2025-09-29T09:45:06.000Z",
        "edit_controls": {
          "editable_until": "2025-09-29T10:45:06.000Z",
          "edits_remaining": 5,
          "is_edit_eligible": true
        },
        "edit_history_tweet_ids": [
          "1972598501847847301"
        ],
        "entities": {},
        "geo": {},
        "id": "1972598501847847301",
        "lang": "zh",
        "note_tweet": {
          "entities": {}
        },
        "possibly_sensitive": false,
        "public_metrics": {
          "bookmark_count": 0,
          "impression_count": 0,
          "like_count": 0,
          "quote_count": 0,
          "reply_count": 0,
          "retweet_count": 0
        },
        "reply_settings": "everyone",
        "text": "由于最近眠大人最近再网上和多人吵架，收到不明快递之后以为是炸弹💣(≧ω≦)/"
      }
    ],
    "users": [
      {
        "created_at": "2024-06-24T22:54:46.000Z",
        "description": "偷吃你的大脑🧠",
        "id": "1805373961020260353",
        "location": "基沃托斯",
        "name": "素素素素素",
        "pinned_tweet_id": "1966106570057724087",
        "profile_image_url": "https://pbs.twimg.com/profile_images/1953831631527325697/Wer-X8a4_normal.jpg",
        "protected": false,
        "public_metrics": {
          "followers_count": 1507,
          "following_count": 511,
          "like_count": 7132,
          "listed_count": 4,
          "media_count": 177,
          "tweet_count": 1617
        },
        "username": "ciyou9443",
        "verified": false
      }
    ]
  }
}