{
  "data": {
    "article": {},
    "attachments": {},
    "author_id": "1805373961020260353",
    "conversation_id": "2005126268388606143",
    "created_at": "2025-12-28T04:45:43.000Z",
    "edit_controls": {
      "editable_until": "2025-12-28T05:45:43.000Z",
      "edits_remaining": 5,
      "is_edit_eligible": false
    },
    "edit_history_tweet_ids": [
      "2005138068278510013"
    ],
    "entities": {
      "mentions": [
        {
          "end": 14,
          "id": "1346974977434771460",
          "start": 0,
          "username": "N0rthern_Land"
        }
      ]
    },
    "geo": {},
    "id": "2005138068278510013",
    "in_reply_to_user_id": "1346974977434771460",
    "lang": "zh",
    "note_tweet": {
      "entities": {}
    },
    "possibly_sensitive": false,
    "public_metrics": {
      "bookmark_count": 0,
      "impression_count": 0,
      "like_count": 0,
      "quote_count": 0,
      "reply_count": 0,
      "retweet_count": 0
    },
    "referenced_tweets": [
      {
        "id": "2005126268388606143",
        "type": "replied_to"
      }
    ],
    "reply_settings": "everyone",
    "text": "@N0rthern_Land 贴贴"
  },
  "includes": {
    "tweets": [
      {
        "article": {},
        "attachments": {},
        "author_id": "1805373961020260353",
        "conversation_id": "2005126268388606143",
        "created_at": "2025-12-28T04:45:43.000Z",
        "edit_controls": {
          "editable_until": "2025-12-28T05:45:43.000Z",
          "edits_remaining": 5,
          "is_edit_eligible": false
        },
        "edit_history_tweet_ids": [
          "2005138068278510013"
        ],
        "entities": {
          "mentions": [
            {
              "end": 14,
              "id": "1346974977434771460",
              "start": 0,
              "username": "N0rthern_Land"
            }
          ]
        },
        "geo": {},
        "id": "2005138068278510013",
        "in_reply_to_user_id": "1346974977434771460",
        "lang": "zh",
        "note_tweet": {
          "entities": {}
        },
        "possibly_sensitive": false,
        "public_metrics": {
          "bookmark_count": 0,
          "impression_count": 0,
          "like_count": 0,
          "quote_count": 0,
          "reply_count": 0,
          "retweet_count": 0
        },
        "referenced_tweets": [
          {
            "id": "2005126268388606143",
            "type": "replied_to"
          }
        ],
        "reply_settings": "everyone",
        "text": "@N0rthern_Land 贴贴"
      },
      {
        "article": {},
        "attachments": {},
        "author_id": "1346974977434771460",
        "conversation_id": "2005126268388606143",
        "created_at": "2025-12-28T03:58:50.000Z",
        "edit_controls": {
          "editable_until": "2025-12-28T04:58:50.000Z",
          "edits_remaining": 5,
          "is_edit_eligible": true
        },
        "edit_history_tweet_ids": [
          "2005126268388606143"
        ],
        "entities": {},
        "geo": {},
        "id": "2005126268388606143",
        "lang": "zh",
        "note_tweet": {
          "entities": {}
        },
        "possibly_sensitive": false,
        "public_metrics": {
          "bookmark_count": 0,
          "impression_count": 281,
          "like_count": 19,
          "quote_count": 0,
          "reply_count": 1,
          "retweet_count": 0
        },
        "reply_settings": "everyone",
        "text": "现在不喜欢跟人辩解，我会表达自己的观点看法，但是支教没必要，有这个时间我多评论点赞几个美少女人家善良的跟我贴贴多好"
      }
    ],
    "users": [
      {
        "created_at": "2024-06-24T22:54:46.000Z",
        "description": "主包傻fufu的所以会偷吃你的大脑🧠",
        "id": "1805373961020260353",
        "location": "基沃托斯",
        "name": "素素素素素",
        "profile_image_url": "https://pbs.twimg.com/profile_images/1980223146952183808/kEXCopJn_normal.jpg",
        "protected": false,
        "public_metrics": {
          "followers_count": 1539,
          "following_count": 538,
          "like_count": 9677,
          "listed_count": 4,
          "media_count": 316,
          "tweet_count": 2376
        },
        "username": "ciyou9443",
        "verified": false
      },
      {
        "created_at": "2021-01-07T00:20:49.000Z",
        "description": "从那不勒斯到今天走了有多远/🏳️‍🌈/粉红和看黄男别关注我/女朋友@ayashikinoco/私信移步里账@san45142",
        "entities": {
          "description": {
            "mentions": [
              {
                "end": 46,
                "start": 33,
                "username": "ayashikinoco"
              },
              {
                "end": 62,
                "start": 53,
                "username": "san45142"
              }
            ]
          }
        },
        "id": "1346974977434771460",
        "name": "北长尾山雀",
        "pinned_tweet_id": "1777993830031302950",
        "profile_image_url": "https://pbs.twimg.com/profile_images/1995463213237125120/wvHDfzkU_normal.jpg",
        "protected": false,
        "public_metrics": {
          "followers_count": 63213,
          "following_count": 806,
          "like_count": 99594,
          "listed_count": 150,
          "media_count": 3353,
          "tweet_count": 32073
        },
        "username": "N0rthern_Land",
        "verified": true
      }
    ]
  }
}