{
  "data": {
    "article": {},
    "attachments": {
      "media_keys": [
        "3_2050264322165915648",
        "3_2050264321016705024",
        "3_2050264321385713665",
        "3_2050264321448714240"
      ]
    },
    "author_id": "1805373961020260353",
    "conversation_id": "2050264325131297235",
    "created_at": "2026-05-01T17:21:21.000Z",
    "edit_controls": {
      "editable_until": "2026-05-01T18:21:21.000Z",
      "edits_remaining": 5,
      "is_edit_eligible": true
    },
    "edit_history_tweet_ids": [
      "2050264325131297235"
    ],
    "entities": {
      "urls": [
        {
          "display_url": "pic.x.com/TzQuRoa8Bc",
          "end": 36,
          "expanded_url": "https://x.com/ciyou9443/status/2050264325131297235/photo/1",
          "media_key": "3_2050264322165915648",
          "start": 13,
          "url": "https://t.co/TzQuRoa8Bc"
        },
        {
          "display_url": "pic.x.com/TzQuRoa8Bc",
          "end": 36,
          "expanded_url": "https://x.com/ciyou9443/status/2050264325131297235/photo/1",
          "media_key": "3_2050264321016705024",
          "start": 13,
          "url": "https://t.co/TzQuRoa8Bc"
        },
        {
          "display_url": "pic.x.com/TzQuRoa8Bc",
          "end": 36,
          "expanded_url": "https://x.com/ciyou9443/status/2050264325131297235/photo/1",
          "media_key": "3_2050264321385713665",
          "start": 13,
          "url": "https://t.co/TzQuRoa8Bc"
        },
        {
          "display_url": "pic.x.com/TzQuRoa8Bc",
          "end": 36,
          "expanded_url": "https://x.com/ciyou9443/status/2050264325131297235/photo/1",
          "media_key": "3_2050264321448714240",
          "start": 13,
          "url": "https://t.co/TzQuRoa8Bc"
        }
      ]
    },
    "geo": {},
    "id": "2050264325131297235",
    "lang": "zh",
    "note_tweet": {
      "entities": {}
    },
    "possibly_sensitive": false,
    "public_metrics": {
      "bookmark_count": 0,
      "impression_count": 0,
      "like_count": 0,
      "quote_count": 0,
      "reply_count": 0,
      "retweet_count": 0
    },
    "reply_settings": "everyone",
    "text": "找回了一些和猫一起的老图 https://t.co/TzQuRoa8Bc"
  },
  "includes": {
    "media": [
      {
        "height": 2048,
        "media_key": "3_2050264322165915648",
        "public_metrics": {},
        "type": "photo",
        "url": "https://pbs.twimg.com/media/HHQAicpbQAAa7CJ.jpg",
        "width": 1152
      },
      {
        "height": 1151,
        "media_key": "3_2050264321016705024",
        "public_metrics": {},
        "type": "photo",
        "url": "https://pbs.twimg.com/media/HHQAiYXbsAA0GnS.jpg",
        "width": 2048
      },
      {
        "height": 1152,
        "media_key": "3_2050264321385713665",
        "public_metrics": {},
        "type": "photo",
        "url": "https://pbs.twimg.com/media/HHQAiZvaUAEzm3F.jpg",
        "width": 2048
      },
      {
        "height": 1920,
        "media_key": "3_2050264321448714240",
        "public_metrics": {},
        "type": "photo",
        "url": "https://pbs.twimg.com/media/HHQAiZ-boAAJFdz.jpg",
        "width": 1080
      }
    ],
    "tweets": [
      {
        "article": {},
        "attachments": {
          "media_keys": [
            "3_2050264322165915648",
            "3_2050264321016705024",
            "3_2050264321385713665",
            "3_2050264321448714240"
          ]
        },
        "author_id": "1805373961020260353",
        "conversation_id": "2050264325131297235",
        "created_at": "2026-05-01T17:21:21.000Z",
        "edit_controls": {
          "editable_until": "2026-05-01T18:21:21.000Z",
          "edits_remaining": 5,
          "is_edit_eligible": true
        },
        "edit_history_tweet_ids": [
          "2050264325131297235"
        ],
        "entities": {
          "urls": [
            {
              "display_url": "pic.x.com/TzQuRoa8Bc",
              "end": 36,
              "expanded_url": "https://x.com/ciyou9443/status/2050264325131297235/photo/1",
              "media_key": "3_2050264322165915648",
              "start": 13,
              "url": "https://t.co/TzQuRoa8Bc"
            },
            {
              "display_url": "pic.x.com/TzQuRoa8Bc",
              "end": 36,
              "expanded_url": "https://x.com/ciyou9443/status/2050264325131297235/photo/1",
              "media_key": "3_2050264321016705024",
              "start": 13,
              "url": "https://t.co/TzQuRoa8Bc"
            },
            {
              "display_url": "pic.x.com/TzQuRoa8Bc",
              "end": 36,
              "expanded_url": "https://x.com/ciyou9443/status/2050264325131297235/photo/1",
              "media_key": "3_2050264321385713665",
              "start": 13,
              "url": "https://t.co/TzQuRoa8Bc"
            },
            {
              "display_url": "pic.x.com/TzQuRoa8Bc",
              "end": 36,
              "expanded_url": "https://x.com/ciyou9443/status/2050264325131297235/photo/1",
              "media_key": "3_2050264321448714240",
              "start": 13,
              "url": "https://t.co/TzQuRoa8Bc"
            }
          ]
        },
        "geo": {},
        "id": "2050264325131297235",
        "lang": "zh",
        "note_tweet": {
          "entities": {}
        },
        "possibly_sensitive": false,
        "public_metrics": {
          "bookmark_count": 0,
          "impression_count": 0,
          "like_count": 0,
          "quote_count": 0,
          "reply_count": 0,
          "retweet_count": 0
        },
        "reply_settings": "everyone",
        "text": "找回了一些和猫一起的老图 https://t.co/TzQuRoa8Bc"
      }
    ],
    "users": [
      {
        "created_at": "2024-06-24T22:54:46.000Z",
        "description": "病树前头，毁肌销骨 眠眠猫：@hoshinemu123 蓁老师：@ilobius",
        "entities": {
          "description": {
            "mentions": [
              {
                "end": 27,
                "start": 14,
                "username": "hoshinemu123"
              },
              {
                "end": 40,
                "start": 32,
                "username": "ilobius"
              }
            ]
          }
        },
        "id": "1805373961020260353",
        "location": "望舒",
        "name": "常曦",
        "profile_image_url": "https://pbs.twimg.com/profile_images/2045902863415787520/BP3YXPI3_normal.jpg",
        "protected": false,
        "public_metrics": {
          "followers_count": 1541,
          "following_count": 534,
          "like_count": 10696,
          "listed_count": 5,
          "media_count": 384,
          "tweet_count": 2765
        },
        "username": "ciyou9443",
        "verified": false
      }
    ]
  }
}